square/__init__.py
square/__main__.py
dheeraj_square-1.0.1.dist-info/LICENSE
dheeraj_square-1.0.1.dist-info/METADATA
dheeraj_square-1.0.1.dist-info/WHEEL
dheeraj_square-1.0.1.dist-info/entry_points.txt
dheeraj_square-1.0.1.dist-info/top_level.txt
dheeraj_square-1.0.1.dist-info/RECORD
