Metadata-Version: 2.1
Name: dheeraj-square
Version: 1.0.1
Summary: It squares the number
Home-page: UNKNOWN
Author: Dheeraj Rajput
Author-email: kumardheeraj9701@gmail.com
License: MIT
Platform: UNKNOWN
Classifier: License :: OSI Approved :: MIT License
Classifier: Programming Language :: Python :: 3.6
Classifier: Programming Language :: Python :: 3.7
Classifier: Programming Language :: Python :: 3.8
